akasha/akasha.py
akasha-0.0.1.dist-info/WHEEL
akasha-0.0.1.dist-info/METADATA
akasha-0.0.1.dist-info/RECORD
