Metadata-Version: 2.1
Name: akasha
Version: 0.0.1
Summary: Python module for providing game information from different sources.
Home-page: https://github.com/DEViantUA/Akasha-Terminal
Author: None
Requires-Python: >=3.7,<4.0
Classifier: Programming Language :: Python :: 3
Classifier: Programming Language :: Python :: 3.7
Classifier: Programming Language :: Python :: 3.8
Classifier: Programming Language :: Python :: 3.9
Classifier: Programming Language :: Python :: 3.10
Classifier: Programming Language :: Python :: 3.11
Requires-Dist: asyncache (>=0.3.1,<0.4.0)
Requires-Dist: cachetools (>=5.2.0,<6.0.0)
Project-URL: Repository, https://github.com/DEViantUA/Akasha-Terminal
